hierarchybuilder/__init__.py
hierarchybuilder/hierarchy_builder.py
hierarchybuilder/utils.py
hierarchybuilder/DAG/DAG_utils.py
hierarchybuilder/DAG/NounPhraseObject.py
hierarchybuilder/DAG/__init__.py
hierarchybuilder/DAG/hierarchical_structure_algorithms.py
hierarchybuilder/UMLS/__init__.py
hierarchybuilder/UMLS/umls_loader.py
hierarchybuilder/UMLS/umls_services.py
hierarchybuilder/combine_spans/__init__.py
hierarchybuilder/combine_spans/combineSpans.py
hierarchybuilder/combine_spans/combine_nodes_UMLS.py
hierarchybuilder/combine_spans/paraphrase_detection_SAP_BERT.py
hierarchybuilder/combine_spans/utils.py
hierarchybuilder/expansions/__init__.py
hierarchybuilder/expansions/parse_medical_data.py
hierarchybuilder/expansions/valid_expansion.py
hierarchybuilder/expansions/valid_expansion_utils.py
hierarchybuilder/taxonomy/__init__.py
hierarchybuilder/taxonomy/taxonomies_from_UMLS.py
hierarchybuilder/topic_clustering/__init__.py
hierarchybuilder/topic_clustering/main_clustering.py
hierarchybuilder/topic_clustering/utils_clustering.py
hierarchybuilder/visualization/__init__.py
hierarchybuilder/visualization/json_dag_visualization.py
hierarchybuilder/visualization/normalize_quantity.py
hierarchybuilder-0.0.7.dist-info/LICENSE.txt
hierarchybuilder-0.0.7.dist-info/METADATA
hierarchybuilder-0.0.7.dist-info/WHEEL
hierarchybuilder-0.0.7.dist-info/top_level.txt
hierarchybuilder-0.0.7.dist-info/RECORD
