Metadata-Version: 2.1
Name: hierarchybuilder
Version: 0.0.7
Summary: implementation of hierarchy builder
Home-page: https://github.com/itayair//hierarchybuilder
Author: Itay Yair and Hillel Taub-Tabib and Yoav Goldberg
Author-email: iy24592@gmail.com
License: MIT
Project-URL: Bug Tracker, https://github.com/itayair/hierarchybuilder/-/issues
Classifier: Programming Language :: Python :: 3
Classifier: License :: OSI Approved :: MIT License
Classifier: Operating System :: OS Independent
Requires-Python: >=3.7
License-File: LICENSE.txt
Requires-Dist: fastapi (==0.94.1)
Requires-Dist: nltk (==3.8.1)
Requires-Dist: pandas (==1.5.3)
Requires-Dist: quantulum3 (==0.8.1)
Requires-Dist: requests (==2.28.2)
Requires-Dist: scikit-learn (==1.2.0)
Requires-Dist: setuptools (==60.2.0)
Requires-Dist: spacy (==3.0.9)
Requires-Dist: torch (==1.13.1)
Requires-Dist: tqdm (==4.64.1)
Requires-Dist: transformers (==4.26.1)
Requires-Dist: uvicorn (==0.21.0)
